{
  "jobId": "a2c95caa-c5b5-40db-9685-8038f9b9e3a9",
  "timestamp": "2026-03-17T16:41:39.680Z",
  "totalPipelineDurationMs": 28912,
  "totalPipelineDurationSec": "28.91s",
  "tasks": {
    "Init Pipeline & State": {
      "start": "2026-03-17T16:41:10.768Z",
      "end": "2026-03-17T16:41:10.768Z",
      "durationSec": "INCOMPLETE"
    },
    "Character Streaming Setup": {
      "start": "2026-03-17T16:41:10.768Z",
      "end": "2026-03-17T16:41:10.770Z",
      "durationSec": "0.00s"
    },
    "Rounds Streaming Setup": {
      "start": "2026-03-17T16:41:10.770Z",
      "end": "2026-03-17T16:41:10.771Z",
      "durationSec": "0.00s"
    },
    "Meta Generation": {
      "start": "2026-03-17T16:41:10.771Z",
      "end": "2026-03-17T16:41:14.816Z",
      "durationSec": "4.04s"
    },
    "Thumbnail Image Gen": {
      "start": "2026-03-17T16:41:15.219Z",
      "end": "2026-03-17T16:41:18.703Z",
      "durationSec": "3.48s"
    },
    "Round 1 Generation (Images+Audio)": {
      "start": "2026-03-17T16:41:19.174Z",
      "end": "2026-03-17T16:41:22.429Z",
      "durationSec": "3.25s"
    },
    "Round 1 attacker image": {
      "start": "2026-03-17T16:41:19.174Z",
      "end": "2026-03-17T16:41:22.361Z",
      "durationSec": "3.19s"
    },
    "Round 1 opponent image": {
      "start": "2026-03-17T16:41:19.174Z",
      "end": "2026-03-17T16:41:22.429Z",
      "durationSec": "3.25s"
    },
    "Round 1 audio": {
      "start": "2026-03-17T16:41:19.174Z",
      "end": "2026-03-17T16:41:20.949Z",
      "durationSec": "1.77s"
    },
    "Char 1 [Goku] Image Gen": {
      "start": "2026-03-17T16:41:20.470Z",
      "end": "2026-03-17T16:41:23.387Z",
      "durationSec": "2.92s"
    },
    "Round 1 Audio Duration Fetch": {
      "start": "2026-03-17T16:41:22.429Z",
      "end": "2026-03-17T16:41:22.518Z",
      "durationSec": "0.09s"
    },
    "Round 1 State Emitted": {
      "start": "2026-03-17T16:41:22.518Z",
      "end": "2026-03-17T16:41:22.569Z",
      "durationSec": "0.05s"
    },
    "Round 2 Generation (Images+Audio)": {
      "start": "2026-03-17T16:41:22.575Z",
      "end": "2026-03-17T16:41:25.380Z",
      "durationSec": "2.81s"
    },
    "Round 2 attacker image": {
      "start": "2026-03-17T16:41:22.575Z",
      "end": "2026-03-17T16:41:25.380Z",
      "durationSec": "2.81s"
    },
    "Round 2 opponent image": {
      "start": "2026-03-17T16:41:22.575Z",
      "end": "2026-03-17T16:41:25.361Z",
      "durationSec": "2.79s"
    },
    "Round 2 audio": {
      "start": "2026-03-17T16:41:22.575Z",
      "end": "2026-03-17T16:41:24.387Z",
      "durationSec": "1.81s"
    },
    "Announcer Init & Audio Check": {
      "start": "2026-03-17T16:41:23.387Z",
      "end": "2026-03-17T16:41:23.944Z",
      "durationSec": "0.56s"
    },
    "Char 1 [Goku] State Emitted": {
      "start": "2026-03-17T16:41:23.944Z",
      "end": "2026-03-17T16:41:24.056Z",
      "durationSec": "0.11s"
    },
    "Char 2 [Vegeta] Image Gen": {
      "start": "2026-03-17T16:41:24.083Z",
      "end": "2026-03-17T16:41:26.977Z",
      "durationSec": "2.89s"
    },
    "Round 2 Audio Duration Fetch": {
      "start": "2026-03-17T16:41:25.380Z",
      "end": "2026-03-17T16:41:25.430Z",
      "durationSec": "0.05s"
    },
    "Round 2 State Emitted": {
      "start": "2026-03-17T16:41:25.430Z",
      "end": "2026-03-17T16:41:25.487Z",
      "durationSec": "0.06s"
    },
    "Round 3 Generation (Images+Audio)": {
      "start": "2026-03-17T16:41:25.488Z",
      "end": "2026-03-17T16:41:28.296Z",
      "durationSec": "2.81s"
    },
    "Round 3 attacker image": {
      "start": "2026-03-17T16:41:25.488Z",
      "end": "2026-03-17T16:41:28.275Z",
      "durationSec": "2.79s"
    },
    "Round 3 opponent image": {
      "start": "2026-03-17T16:41:25.488Z",
      "end": "2026-03-17T16:41:28.296Z",
      "durationSec": "2.81s"
    },
    "Round 3 audio": {
      "start": "2026-03-17T16:41:25.488Z",
      "end": "2026-03-17T16:41:27.235Z",
      "durationSec": "1.75s"
    },
    "Char 2 [Vegeta] State Emitted": {
      "start": "2026-03-17T16:41:26.977Z",
      "end": "2026-03-17T16:41:27.028Z",
      "durationSec": "0.05s"
    },
    "Round 3 Audio Duration Fetch": {
      "start": "2026-03-17T16:41:28.296Z",
      "end": "2026-03-17T16:41:28.343Z",
      "durationSec": "0.05s"
    },
    "Round 3 State Emitted": {
      "start": "2026-03-17T16:41:28.343Z",
      "end": "2026-03-17T16:41:28.398Z",
      "durationSec": "0.06s"
    },
    "Round 4 Generation (Images+Audio)": {
      "start": "2026-03-17T16:41:28.400Z",
      "end": "2026-03-17T16:41:31.235Z",
      "durationSec": "2.83s"
    },
    "Round 4 attacker image": {
      "start": "2026-03-17T16:41:28.400Z",
      "end": "2026-03-17T16:41:31.235Z",
      "durationSec": "2.83s"
    },
    "Round 4 opponent image": {
      "start": "2026-03-17T16:41:28.400Z",
      "end": "2026-03-17T16:41:31.212Z",
      "durationSec": "2.81s"
    },
    "Round 4 audio": {
      "start": "2026-03-17T16:41:28.400Z",
      "end": "2026-03-17T16:41:30.136Z",
      "durationSec": "1.74s"
    },
    "Round 4 Audio Duration Fetch": {
      "start": "2026-03-17T16:41:31.235Z",
      "end": "2026-03-17T16:41:31.480Z",
      "durationSec": "0.24s"
    },
    "Round 4 State Emitted": {
      "start": "2026-03-17T16:41:31.480Z",
      "end": "2026-03-17T16:41:31.584Z",
      "durationSec": "0.10s"
    },
    "Round 5 Generation (Images+Audio)": {
      "start": "2026-03-17T16:41:31.600Z",
      "end": "2026-03-17T16:41:34.542Z",
      "durationSec": "2.94s"
    },
    "Round 5 attacker image": {
      "start": "2026-03-17T16:41:31.600Z",
      "end": "2026-03-17T16:41:34.542Z",
      "durationSec": "2.94s"
    },
    "Round 5 opponent image": {
      "start": "2026-03-17T16:41:31.601Z",
      "end": "2026-03-17T16:41:34.462Z",
      "durationSec": "2.86s"
    },
    "Round 5 audio": {
      "start": "2026-03-17T16:41:31.601Z",
      "end": "2026-03-17T16:41:33.937Z",
      "durationSec": "2.34s"
    },
    "Round 5 Audio Duration Fetch": {
      "start": "2026-03-17T16:41:34.542Z",
      "end": "2026-03-17T16:41:34.587Z",
      "durationSec": "0.04s"
    },
    "Round 5 State Emitted": {
      "start": "2026-03-17T16:41:34.587Z",
      "end": "2026-03-17T16:41:34.653Z",
      "durationSec": "0.07s"
    },
    "Round 6 Generation (Images+Audio)": {
      "start": "2026-03-17T16:41:34.657Z",
      "end": "2026-03-17T16:41:37.911Z",
      "durationSec": "3.25s"
    },
    "Round 6 attacker image": {
      "start": "2026-03-17T16:41:34.657Z",
      "end": "2026-03-17T16:41:37.911Z",
      "durationSec": "3.25s"
    },
    "Round 6 opponent image": {
      "start": "2026-03-17T16:41:34.657Z",
      "end": "2026-03-17T16:41:37.878Z",
      "durationSec": "3.22s"
    },
    "Round 6 audio": {
      "start": "2026-03-17T16:41:34.658Z",
      "end": "2026-03-17T16:41:36.343Z",
      "durationSec": "1.69s"
    },
    "Round 6 Audio Duration Fetch": {
      "start": "2026-03-17T16:41:37.911Z",
      "end": "2026-03-17T16:41:37.966Z",
      "durationSec": "0.06s"
    },
    "Round 6 State Emitted": {
      "start": "2026-03-17T16:41:37.966Z",
      "end": "2026-03-17T16:41:38.025Z",
      "durationSec": "0.06s"
    }
  }
}